pygamepal/__init__.py
pygamepal/animation.py
pygamepal/animator.py
pygamepal/button.py
pygamepal/camera.py
pygamepal/collider.py
pygamepal/dialogue.py
pygamepal/dialoguePage.py
pygamepal/drawText.py
pygamepal/easingFunctions.py
pygamepal/flatten.py
pygamepal/game.py
pygamepal/globals.py
pygamepal/input.py
pygamepal/lightMask.png
pygamepal/lighting.py
pygamepal/particle.py
pygamepal/particleEmitter.py
pygamepal/scene.py
pygamepal/splitTexture.py
pygamepal/sprite.py
pygamepal/spriteImage.py
pygamepal/spriteTextureList.py
pygamepal/transition.py
pygamepal/trigger.py
pygamepal-1.1.1.dist-info/METADATA
pygamepal-1.1.1.dist-info/WHEEL
pygamepal-1.1.1.dist-info/licenses/LICENSE
pygamepal-1.1.1.dist-info/RECORD
