Metadata-Version: 2.4
Name: pygamepal
Version: 1.1.1
Summary: A library of classes and helper functions to support game development in Pygame
Project-URL: Homepage, https://github.com/rik-cross/pygamepal
Project-URL: Suggestions and bugs, https://github.com/rik-cross/pygamepal/issues
Author-email: Rik Cross <rik.j.cross@gmail.com>
License-File: LICENSE
Classifier: License :: OSI Approved :: MIT License
Classifier: Operating System :: OS Independent
Classifier: Programming Language :: Python :: 3
Requires-Python: >=3.7
Requires-Dist: pygame-ce
